examples/__init__.py
utype/__init__.py
utype/decorator.py
utype/schema.py
utype/settings.py
utype/types.py
utype/parser/__init__.py
utype/parser/base.py
utype/parser/cls.py
utype/parser/field.py
utype/parser/func.py
utype/parser/options.py
utype/parser/rule.py
utype/specs/__init__.py
utype/specs/json_schema/__init__.py
utype/specs/json_schema/constant.py
utype/specs/json_schema/generator.py
utype/specs/json_schema/parser.py
utype/specs/python/__init__.py
utype/specs/python/generator.py
utype/utils/__init__.py
utype/utils/base.py
utype/utils/compat.py
utype/utils/datastructures.py
utype/utils/encode.py
utype/utils/example.py
utype/utils/exceptions.py
utype/utils/functional.py
utype/utils/style.py
utype/utils/transform.py
utype-0.6.8.dist-info/LICENSE
utype-0.6.8.dist-info/METADATA
utype-0.6.8.dist-info/WHEEL
utype-0.6.8.dist-info/top_level.txt
utype-0.6.8.dist-info/RECORD
