Metadata-Version: 2.1
Name: utype
Version: 0.6.8
Summary: Declare & parse types / dataclasses / functions based on Python type annotations
Home-page: https://utype.io
Author: XuLin Zhou
Author-email: zxl@utilmeta.com
License: Apache 2.0
Project-URL: Project Home, https://utype.io
Project-URL: Documentation, https://utype.io
Project-URL: Source Code, https://github.com/utilmeta/utype
Keywords: utype type schema meta-type validation data-model type-transform parser json-schema
Classifier: Development Status :: 3 - Alpha
Classifier: Programming Language :: Python
Classifier: Programming Language :: Python :: 3
Classifier: Programming Language :: Python :: 3 :: Only
Classifier: Programming Language :: Python :: 3.7
Classifier: Programming Language :: Python :: 3.8
Classifier: Programming Language :: Python :: 3.9
Classifier: Programming Language :: Python :: 3.10
Classifier: Programming Language :: Python :: 3.11
Classifier: Intended Audience :: Developers
Classifier: Intended Audience :: Information Technology
Classifier: Intended Audience :: System Administrators
Classifier: License :: OSI Approved :: Apache Software License
Classifier: Operating System :: OS Independent
Classifier: Topic :: Software Development :: Libraries :: Python Modules
Classifier: Topic :: Internet
Requires-Python: >=3.7
License-File: LICENSE
Requires-Dist: typing-extensions (>=4.1.0)
